unixlog/__init__.py
unixlog/ulog.py
unixlog-0.0.2.dist-info/LICENSE
unixlog-0.0.2.dist-info/METADATA
unixlog-0.0.2.dist-info/WHEEL
unixlog-0.0.2.dist-info/top_level.txt
unixlog-0.0.2.dist-info/RECORD
