Metadata-Version: 2.1
Name: unixlog
Version: 0.0.2
Summary: Python program prints unix style logging on terminal
Home-page: https://github.com/raahoolkumeriya/unixlog
Author: Raahool Kumeriya
Author-email: rahul.kumeriya@outlook.com
License: UNKNOWN
Project-URL: Bug Tracker, https://github.com/raahoolkumeriya/unixlog/issues
Platform: UNKNOWN
Classifier: Programming Language :: Python :: 3
Classifier: License :: OSI Approved :: MIT License
Classifier: Operating System :: OS Independent
Requires-Python: >=3.0
License-File: LICENSE
Requires-Dist: colorama
